helpme/__init__.py
helpme/__version__.py
helpme/admin.py
helpme/apps.py
helpme/config.py
helpme/forms.py
helpme/mixins.py
helpme/models.py
helpme/settings.py
helpme/tests.py
helpme/utils.py
helpme/api/__init__.py
helpme/api/serializers.py
helpme/api/urls.py
helpme/api/views.py
helpme/locale/ja/LC_MESSAGES/django.po
helpme/migrations/0001_initial.py
helpme/migrations/0002_category_question.py
helpme/migrations/0003_auto_20200901_2025.py
helpme/migrations/0004_auto_20200901_2323.py
helpme/migrations/0005_auto_20200908_2229.py
helpme/migrations/0006_auto_20200911_0010.py
helpme/migrations/0007_auto_20200912_0509.py
helpme/migrations/0008_auto_20200930_2347.py
helpme/migrations/0009_auto_20201001_1913.py
helpme/migrations/0010_auto_20201009_0000.py
helpme/migrations/0011_auto_20201106_2238.py
helpme/migrations/0012_auto_20210616_2150.py
helpme/migrations/0013_alter_ticket_related_to.py
helpme/migrations/0014_alter_ticket_related_to.py
helpme/migrations/__init__.py
helpme/static/js/support/main.js
helpme/templates/helpme/admin_ticket_list.html
helpme/templates/helpme/anonymous_ticket.html
helpme/templates/helpme/base.html
helpme/templates/helpme/event_comment.txt
helpme/templates/helpme/faq.html
helpme/templates/helpme/faq_create.html
helpme/templates/helpme/support_email.html
helpme/templates/helpme/team_detail.html
helpme/templates/helpme/team_form.html
helpme/templates/helpme/ticket_detail.html
helpme/templates/helpme/ticket_form.html
helpme/templates/helpme/ticket_list.html
helpme/templates/helpme/email/anonymous_ticket.txt
helpme/templates/helpme/email/user_ticket.txt
helpme/templates/helpme/includes/user_meta.html
helpme/templatetags/__init__.py
helpme/templatetags/helpme_extras.py
helpme/urls/__init__.py
helpme/urls/helpme.py
helpme/urls/helpme_admin.py
helpme/views/__init__.py
helpme/views/helpme.py
helpme/views/helpme_admin.py
django_help_me-0.1.24.dist-info/LICENSE
django_help_me-0.1.24.dist-info/METADATA
django_help_me-0.1.24.dist-info/WHEEL
django_help_me-0.1.24.dist-info/top_level.txt
django_help_me-0.1.24.dist-info/RECORD
