Metadata-Version: 2.1
Name: django-help-me
Version: 0.1.24
Summary: An app for providing a simple Help Desk & FAQ for users.
Home-page: https://github.com/renderbox/django-help-me/
Author: Grant Viklund, Mackenzie Camisa
Author-email: renderbox@example.com
License: MIT license
Keywords: django,app
Platform: UNKNOWN
Classifier: Development Status :: 2 - Pre-Alpha
Classifier: Intended Audience :: Developers
Classifier: Programming Language :: Python :: 3 :: Only
Classifier: Programming Language :: Python :: 3.6
Classifier: Programming Language :: Python :: 3.7
Requires-Python: >=3.6
Requires-Dist: Django (<4.1,>=3.0)
Requires-Dist: django-autoslug
Requires-Dist: django-multiselectfield
Requires-Dist: django-crispy-forms
Requires-Dist: django-user-agents
Requires-Dist: django-site-configs
Provides-Extra: build
Requires-Dist: setuptools ; extra == 'build'
Requires-Dist: wheel ; extra == 'build'
Requires-Dist: twine ; extra == 'build'
Requires-Dist: m2r ; extra == 'build'
Provides-Extra: dev
Requires-Dist: django-extensions ; extra == 'dev'
Requires-Dist: django-allauth ; extra == 'dev'
Requires-Dist: dj-database-url ; extra == 'dev'
Requires-Dist: psycopg2-binary ; extra == 'dev'
Requires-Dist: pylint ; extra == 'dev'
Requires-Dist: djangorestframework ; extra == 'dev'
Requires-Dist: pyyaml ; extra == 'dev'
Requires-Dist: ua-parser ; extra == 'dev'
Requires-Dist: user-agents ; extra == 'dev'
Provides-Extra: docs
Requires-Dist: recommonmark ; extra == 'docs'
Requires-Dist: m2r ; extra == 'docs'
Requires-Dist: django-extensions ; extra == 'docs'
Requires-Dist: coverage ; extra == 'docs'
Requires-Dist: Sphinx ; extra == 'docs'
Requires-Dist: rstcheck ; extra == 'docs'
Requires-Dist: sphinx-rtd-theme ; extra == 'docs'
Provides-Extra: prod
Provides-Extra: test
